AI_Accel/Neuron/fsm_ctrl.v
// fsm_ctrl.v
// Sequences the MLP pipeline. Each layer is combinational-dot-product + registered-output, so each layer takes exactly 1 clock edge to produce a valid result once its inputs are stable. This FSM exists to make that timing explicit and give a clean "done" pulse, rather than relying on the user to count cycles externally.
//
// States:
//   IDLE         - waiting for START
//   LOAD_INPUT   - input vector is presented to layer 1 this cycle
//   LAYER1_WAIT  - layer 1's registered outputs become valid on this edge
//   LAYER2_WAIT  - layer 2's registered outputs become valid on this edge
//   DONE         - output vector valid, DONE pulses high for 1 cycle

module fsm_ctrl (
    input  clk,
    input  rst,
    input  start,
    output reg done,
    output [2:0] state_out
);

    localparam IDLE        = 3'd0,
               LOAD_INPUT   = 3'd1,
               LAYER1_WAIT  = 3'd2,
               LAYER2_WAIT  = 3'd3,
               DONE_ST      = 3'd4;

    reg [2:0] state;

    always @(posedge clk or posedge rst) begin
        if (rst) begin
            state <= IDLE;
            done  <= 1'b0;
        end
        else begin
            done <= 1'b0;
            case (state)
                IDLE: begin
                    if (start)
                        state <= LOAD_INPUT;
                end

                LOAD_INPUT: begin
                    state <= LAYER1_WAIT;
                end

                LAYER1_WAIT: begin
                    state <= LAYER2_WAIT;
                end

                LAYER2_WAIT: begin
                    state <= DONE_ST;
                end

                DONE_ST: begin
                    done  <= 1'b1;
                    state <= IDLE;
                end

                default: state <= IDLE;
            endcase
        end
    end

    assign state_out = state;

endmodule

AI_Accel/Neuron/neuron.v
// ---------------------------------------------------------------------------
// neuron.v
//
// Generic single neuron: OUT = ReLU( sum_i(X[i]*W[i]) + B )
//
// - N inputs, each DW bits wide (signed), flattened into one bus.
// - Dot product is fully combinational (generate-loop of multipliers +
//   adder tree), registered once at the output on the clock edge.
// - This generalizes AI_Accel/Mac/mac_dot.v and AI_Accel/Neuron/neuron.v,
//   which hardcoded N=4, DW=4 (nibble-packed). Same idea, parameterized.
// ---------------------------------------------------------------------------
module neuron #(
    parameter N      = 4,   // number of inputs to this neuron
    parameter DW     = 8,   // bit width of each input / weight element
    parameter ACC_W  = 32   // accumulator / output width
)(
    input                           clk,
    input                           rst,
    input  signed [N*DW-1:0]        X,   // flattened input vector, element i = X[i*DW +: DW]
    input  signed [N*DW-1:0]        W,   // flattened weight vector, element i = W[i*DW +: DW]
    input  signed [ACC_W-1:0]       B,   // bias
    output reg    signed [ACC_W-1:0] OUT // ReLU(dot + bias), registered
);

    // ---- per-element product, generate loop replaces hand-listed p0..p3 ----
    // each product needs 2*DW bits to not overflow (signed x signed)
    wire signed [2*DW-1:0] prod [0:N-1];

    genvar i;
    generate
        for (i = 0; i < N; i = i + 1) begin : MULT
            assign prod[i] = $signed(X[i*DW +: DW]) * $signed(W[i*DW +: DW]);
        end
    endgenerate

    // ---- adder tree: sum all N products (combinational) ----
    integer k;
    reg signed [ACC_W-1:0] sum_comb;
    always @(*) begin
        sum_comb = {ACC_W{1'b0}};
        for (k = 0; k < N; k = k + 1) begin
            sum_comb = sum_comb + prod[k];
        end
        sum_comb = sum_comb + B;
    end

    // ---- registered ReLU on the clock edge ----
    always @(posedge clk or posedge rst) begin
        if (rst)
            OUT <= {ACC_W{1'b0}};
        else if (sum_comb < 0)
            OUT <= {ACC_W{1'b0}};
        else
            OUT <= sum_comb;
    end

endmodule

AI_Accel/Neuron/neuron_layer.v
// ---------------------------------------------------------------------------
// neuron_layer.v
//
// One fully-connected layer: N_OUT neurons, each fully connected to the
// same N_IN-wide input vector. All neurons computed in parallel (separate
// multiplier hardware per neuron, no time-multiplexing).
//
// Weight/bias layout convention:
//   W_FLAT is N_OUT blocks of (N_IN*DW) bits, one block per neuron:
//     neuron j's weights = W_FLAT[ j*N_IN*DW +: N_IN*DW ]
//   B_FLAT is N_OUT blocks of ACC_W bits, one per neuron's bias.
// ---------------------------------------------------------------------------
module neuron_layer #(
    parameter N_IN   = 4,   // inputs per neuron (= width of input vector)
    parameter N_OUT  = 4,   // number of neurons in this layer
    parameter DW     = 8,   // bit width of each input/weight element
    parameter ACC_W  = 32   // accumulator / output width
)(
    input                                   clk,
    input                                   rst,
    input  signed [N_IN*DW-1:0]             X,       // shared input vector
    input  signed [N_OUT*N_IN*DW-1:0]       W_FLAT,  // all neurons' weights
    input  signed [N_OUT*ACC_W-1:0]         B_FLAT,  // all neurons' biases
    output signed [N_OUT*ACC_W-1:0]         Y_FLAT   // all neurons' outputs
);

    genvar j;
    generate
        for (j = 0; j < N_OUT; j = j + 1) begin : NEURON
            neuron #(
                .N     (N_IN),
                .DW    (DW),
                .ACC_W (ACC_W)
            ) u_neuron (
                .clk (clk),
                .rst (rst),
                .X   (X),
                .W   (W_FLAT[ j*N_IN*DW +: N_IN*DW ]),
                .B   (B_FLAT[ j*ACC_W   +: ACC_W   ]),
                .OUT (Y_FLAT[ j*ACC_W   +: ACC_W   ])
            );
        end
    endgenerate

endmodule

AI_Accel/Neuron/weights_l2.v
// weights_l2.v

// Hardcoded weights + biases for Layer 2 (output layer): 4 inputs -> 2 neurons.
// Inputs here are the requantized (8-bit) outputs of layer 1's neurons. Values chosen to be small and hand-checkable, NOT trained weights.

// Neuron 0 weights: [1, 1, 0, 0]   bias =  0
// Neuron 1 weights: [0, 0, 1, 1]   bias = -2

module weights_l2 #(
    parameter DW    = 8,
    parameter ACC_W = 32
)(
    output signed [2*4*DW-1:0] W_FLAT,   // 2 neurons x 4 weights x DW bits
    output signed [2*ACC_W-1:0] B_FLAT   // 2 neurons x ACC_W bits
);

    // Neuron 0: w = [1,1,0,0], b = 0
    assign W_FLAT[ 0*4*DW +: 4*DW ] = { 8'sd0, 8'sd0, 8'sd1, 8'sd1 };
    assign B_FLAT[ 0*ACC_W +: ACC_W ] = 32'sd0;

    // Neuron 1: w = [0,0,1,1], b = -2
    assign W_FLAT[ 1*4*DW +: 4*DW ] = { 8'sd1, 8'sd1, 8'sd0, 8'sd0 };
    assign B_FLAT[ 1*ACC_W +: ACC_W ] = -32'sd2;

endmodule

AI_Accel/Neuron/requant.v
// requant.v
// Converts one layer's wide accumulator outputs (ACC_W bits, post-ReLU) down to the narrow DW-bit signed format the next layer's neurons expect as input. This is the "requantization" step between layers.

// Method: saturate to the representable DW-bit signed range, rather than truncate. Truncating silently wraps large values to garbage; saturating clips them to the max/min representable value, which is the safer default for a first bring-up.

// NOTE: since this MLP uses ReLU, every value entering here is >= 0, so we only need to saturate the upper bound (no negative clipping needed here). Kept the lower bound check anyway for safety / reuse with non-ReLU layers.

module requant #(
    parameter N      = 4,   //layer width
    parameter ACC_W  = 32,  //incoming width\element
    parameter DW     = 8    //outgoing width\element
)(
    input  signed [N*ACC_W-1:0] IN_FLAT,
    output signed [N*DW-1:0]    OUT_FLAT
);

    localparam signed [DW-1:0] MAX_VAL = {1'b0, {DW-1{1'b1}}};
    localparam signed [DW-1:0] MIN_VAL = {1'b1, {DW-1{1'b0}}};

    genvar i;
    generate
        for (i = 0; i < N; i = i + 1) begin : SAT
            wire signed [ACC_W-1:0] val = IN_FLAT[i*ACC_W +: ACC_W];

            assign OUT_FLAT[i*DW +: DW] =
                (val > $signed({{(ACC_W-DW){1'b0}}, MAX_VAL})) ? MAX_VAL :
                (val < $signed({{(ACC_W-DW){1'b1}}, MIN_VAL})) ? MIN_VAL :
                val[DW-1:0];
        end
    endgenerate

endmodule

AI_Accel/Neuron/weights_l1.v
// weights_l1.v
// Hardcoded weights + biases for Layer 1 (hidden layer): 4 inputs -> 4 neurons. Values chosen to be small and hand-checkable, NOT trained weights.

// Layout: neuron j's 4 weights are W_FLAT[ j*4*DW +: 4*DW ], stored with element 0 in the lowest bits (matches X[0*DW +: DW] convention in neuron.v).

// Neuron 0 weights: [1, 1, 1, 1]   bias =  0
// Neuron 1 weights: [1,-1, 1,-1]   bias =  0
// Neuron 2 weights: [2, 0, 0, 0]   bias = -3
// Neuron 3 weights: [0, 0, 0, 2]   bias =  1

module weights_l1 #(
    parameter DW    = 8,
    parameter ACC_W = 32
)(
    output signed [4*4*DW-1:0] W_FLAT,   // 4 neurons x 4 weights x DW bits
    output signed [4*ACC_W-1:0] B_FLAT   // 4 neurons x ACC_W bits
);

    // Neuron 0: w = [1,1,1,1], b = 0
    assign W_FLAT[ 0*4*DW +: 4*DW ] = { 8'sd1, 8'sd1, 8'sd1, 8'sd1 };
    assign B_FLAT[ 0*ACC_W +: ACC_W ] = 32'sd0;

    // Neuron 1: w = [1,-1,1,-1], b = 0
    assign W_FLAT[ 1*4*DW +: 4*DW ] = { -8'sd1, 8'sd1, -8'sd1, 8'sd1 };
    assign B_FLAT[ 1*ACC_W +: ACC_W ] = 32'sd0;

    // Neuron 2: w = [2,0,0,0], b = -3
    assign W_FLAT[ 2*4*DW +: 4*DW ] = { 8'sd0, 8'sd0, 8'sd0, 8'sd2 };
    assign B_FLAT[ 2*ACC_W +: ACC_W ] = -32'sd3;

    // Neuron 3: w = [0,0,0,2], b = 1
    assign W_FLAT[ 3*4*DW +: 4*DW ] = { 8'sd2, 8'sd0, 8'sd0, 8'sd0 };
    assign B_FLAT[ 3*ACC_W +: ACC_W ] = 32'sd1;

endmodule

AI_Accel/Neuron/mlp_top.v
// mlp_top.v
// Top-level 4 -> 4 -> 2 MLP, fixed-point INT8 in/weights, INT32 accumulate, ReLU on both layers, hardcoded ROM weights.
// Pipeline (see fsm_ctrl.v for state timing):
//   X (4x8b) --> [layer1: 4 neurons, 4-wide dot] --> Y1 (4x32b, ReLU'd)
//             --> [requant: 32b -> 8b, saturating] --> Y1q (4x8b)
//             --> [layer2: 2 neurons, 4-wide dot] --> Y2 (2x32b, ReLU'd)
//                 = final output

module mlp_top #(
    parameter DW    = 8,
    parameter ACC_W = 32
)(
    input                        clk,
    input                        rst,
    input                        start,
    input  signed [4*DW-1:0]     X_IN,
    output signed [2*ACC_W-1:0]  Y_OUT,
    output                       done,
    output [2:0]                 dbg_state
);

    wire signed [4*4*DW-1:0]  l1_W;
    wire signed [4*ACC_W-1:0] l1_B;
    weights_l1 #(.DW(DW), .ACC_W(ACC_W)) u_w1 (.W_FLAT(l1_W), .B_FLAT(l1_B));

    wire signed [4*ACC_W-1:0] l1_Y;
    neuron_layer #(.N_IN(4), .N_OUT(4), .DW(DW), .ACC_W(ACC_W)) u_layer1 (
        .clk    (clk),
        .rst    (rst),
        .X      (X_IN),
        .W_FLAT (l1_W),
        .B_FLAT (l1_B),
        .Y_FLAT (l1_Y)
    );

//Requantize layer1's 32-bit outputs down to 8-bit for layer2
    wire signed [4*DW-1:0] l1_Yq;
    requant #(.N(4), .ACC_W(ACC_W), .DW(DW)) u_requant (
        .IN_FLAT  (l1_Y),
        .OUT_FLAT (l1_Yq)
    );

//Layer 2 weights/bias ROM
    wire signed [2*4*DW-1:0] l2_W;
    wire signed [2*ACC_W-1:0] l2_B;
    weights_l2 #(.DW(DW), .ACC_W(ACC_W)) u_w2 (.W_FLAT(l2_W), .B_FLAT(l2_B));

//Layer 2: 4 in -> 2 out
    neuron_layer #(.N_IN(4), .N_OUT(2), .DW(DW), .ACC_W(ACC_W)) u_layer2 (
        .clk    (clk),
        .rst    (rst),
        .X      (l1_Yq),
        .W_FLAT (l2_W),
        .B_FLAT (l2_B),
        .Y_FLAT (Y_OUT)
    );

    fsm_ctrl u_fsm (
        .clk       (clk),
        .rst       (rst),
        .start     (start),
        .done      (done),
        .state_out (dbg_state)
    );

endmodule

AI_Accel/Neuron/tb_mlp_top.v
`timescale 1ns/1ps

module tb_mlp_top;

    parameter DW    = 8;
    parameter ACC_W = 32;

    reg clk;
    reg rst;
    reg start;
    reg signed [4*DW-1:0] X_IN;
    wire signed [2*ACC_W-1:0] Y_OUT;
    wire done;
    wire [2:0] dbg_state;

    mlp_top #(.DW(DW), .ACC_W(ACC_W)) uut (
        .clk       (clk),
        .rst       (rst),
        .start     (start),
        .X_IN      (X_IN),
        .Y_OUT     (Y_OUT),
        .done      (done),
        .dbg_state (dbg_state)
    );

    wire signed [ACC_W-1:0] y0 = Y_OUT[0*ACC_W +: ACC_W];
    wire signed [ACC_W-1:0] y1 = Y_OUT[1*ACC_W +: ACC_W];

    initial begin
        clk = 0;
        forever #5 clk = ~clk;
    end

    initial begin
        $dumpfile("mlp_top.vcd");
        $dumpvars(0, tb_mlp_top);

        $monitor("Time=%0t state=%0d done=%b X=%h y0=%0d y1=%0d",
                  $time, dbg_state, done, X_IN, y0, y1);

        rst   = 1;
        start = 0;
        X_IN  = 0;
        #12;
        rst = 0;
        #10;

        X_IN  = { 8'sd4, -8'sd1, 8'sd3, 8'sd2 };
        start = 1;
        #10;
        start = 0;

        // wait for done (3 clock edges per fsm_ctrl: LOAD_INPUT->L1->L2->DONE)
        #40;

        X_IN  = { 8'sd0, 8'sd0, 8'sd0, 8'sd0 };
        start = 1;
        #10;
        start = 0;
        #40;

        X_IN  = { 8'sd5, 8'sd5, 8'sd5, 8'sd5 };
        start = 1;
        #10;
        start = 0;
        #40;

        $finish;
    end

endmodule

AI_Accel/Neuron/mlp_top.vcd
$date
	Thu Jun 25 03:26:18 2026
$end
$version
	Icarus Verilog
$end
$timescale
	1ps
$end
$scope module tb_mlp_top $end
$var wire 32 ! y1 [31:0] $end
$var wire 32 " y0 [31:0] $end
$var wire 1 # done $end
$var wire 3 $ dbg_state [2:0] $end
$var wire 64 % Y_OUT [63:0] $end
$var parameter 32 & ACC_W $end
$var parameter 32 ' DW $end
$var reg 32 ( X_IN [31:0] $end
$var reg 1 ) clk $end
$var reg 1 * rst $end
$var reg 1 + start $end
$scope module uut $end
$var wire 32 , X_IN [31:0] $end
$var wire 1 ) clk $end
$var wire 1 * rst $end
$var wire 1 + start $end
$var wire 64 - l2_W [63:0] $end
$var wire 64 . l2_B [63:0] $end
$var wire 32 / l1_Yq [31:0] $end
$var wire 128 0 l1_Y [127:0] $end
$var wire 128 1 l1_W [127:0] $end
$var wire 128 2 l1_B [127:0] $end
$var wire 1 # done $end
$var wire 3 3 dbg_state [2:0] $end
$var wire 64 4 Y_OUT [63:0] $end
$var parameter 32 5 ACC_W $end
$var parameter 32 6 DW $end
$scope module u_fsm $end
$var wire 1 ) clk $end
$var wire 1 * rst $end
$var wire 1 + start $end
$var wire 3 7 state_out [2:0] $end
$var parameter 3 8 DONE_ST $end
$var parameter 3 9 IDLE $end
$var parameter 3 : LAYER1_WAIT $end
$var parameter 3 ; LAYER2_WAIT $end
$var parameter 3 < LOAD_INPUT $end
$var reg 1 # done $end
$var reg 3 = state [2:0] $end
$upscope $end
$scope module u_layer1 $end
$var wire 32 > X [31:0] $end
$var wire 1 ) clk $end
$var wire 1 * rst $end
$var wire 128 ? Y_FLAT [127:0] $end
$var wire 128 @ W_FLAT [127:0] $end
$var wire 128 A B_FLAT [127:0] $end
$var parameter 32 B ACC_W $end
$var parameter 32 C DW $end
$var parameter 32 D N_IN $end
$var parameter 32 E N_OUT $end
$scope begin NEURON[0] $end
$var parameter 2 F j $end
$scope module u_neuron $end
$var wire 32 G B [31:0] $end
$var wire 32 H W [31:0] $end
$var wire 32 I X [31:0] $end
$var wire 1 ) clk $end
$var wire 1 * rst $end
$var parameter 32 J ACC_W $end
$var parameter 32 K DW $end
$var parameter 32 L N $end
$var reg 32 M OUT [31:0] $end
$var reg 32 N sum_comb [31:0] $end
$var integer 32 O k [31:0] $end
$scope begin MULT[0] $end
$var parameter 2 P i $end
$upscope $end
$scope begin MULT[1] $end
$var parameter 2 Q i $end
$upscope $end
$scope begin MULT[2] $end
$var parameter 3 R i $end
$upscope $end
$scope begin MULT[3] $end
$var parameter 3 S i $end
$upscope $end
$upscope $end
$upscope $end
$scope begin NEURON[1] $end
$var parameter 2 T j $end
$scope module u_neuron $end
$var wire 32 U B [31:0] $end
$var wire 32 V W [31:0] $end
$var wire 32 W X [31:0] $end
$var wire 1 ) clk $end
$var wire 1 * rst $end
$var parameter 32 X ACC_W $end
$var parameter 32 Y DW $end
$var parameter 32 Z N $end
$var reg 32 [ OUT [31:0] $end
$var reg 32 \ sum_comb [31:0] $end
$var integer 32 ] k [31:0] $end
$scope begin MULT[0] $end
$var parameter 2 ^ i $end
$upscope $end
$scope begin MULT[1] $end
$var parameter 2 _ i $end
$upscope $end
$scope begin MULT[2] $end
$var parameter 3 ` i $end
$upscope $end
$scope begin MULT[3] $end
$var parameter 3 a i $end
$upscope $end
$upscope $end
$upscope $end
$scope begin NEURON[2] $end
$var parameter 3 b j $end
$scope module u_neuron $end
$var wire 32 c B [31:0] $end
$var wire 32 d W [31:0] $end
$var wire 32 e X [31:0] $end
$var wire 1 ) clk $end
$var wire 1 * rst $end
$var parameter 32 f ACC_W $end
$var parameter 32 g DW $end
$var parameter 32 h N $end
$var reg 32 i OUT [31:0] $end
$var reg 32 j sum_comb [31:0] $end
$var integer 32 k k [31:0] $end
$scope begin MULT[0] $end
$var parameter 2 l i $end
$upscope $end
$scope begin MULT[1] $end
$var parameter 2 m i $end
$upscope $end
$scope begin MULT[2] $end
$var parameter 3 n i $end
$upscope $end
$scope begin MULT[3] $end
$var parameter 3 o i $end
$upscope $end
$upscope $end
$upscope $end
$scope begin NEURON[3] $end
$var parameter 3 p j $end
$scope module u_neuron $end
$var wire 32 q B [31:0] $end
$var wire 32 r W [31:0] $end
$var wire 32 s X [31:0] $end
$var wire 1 ) clk $end
$var wire 1 * rst $end
$var parameter 32 t ACC_W $end
$var parameter 32 u DW $end
$var parameter 32 v N $end
$var reg 32 w OUT [31:0] $end
$var reg 32 x sum_comb [31:0] $end
$var integer 32 y k [31:0] $end
$scope begin MULT[0] $end
$var parameter 2 z i $end
$upscope $end
$scope begin MULT[1] $end
$var parameter 2 { i $end
$upscope $end
$scope begin MULT[2] $end
$var parameter 3 | i $end
$upscope $end
$scope begin MULT[3] $end
$var parameter 3 } i $end
$upscope $end
$upscope $end
$upscope $end
$upscope $end
$scope module u_layer2 $end
$var wire 1 ) clk $end
$var wire 1 * rst $end
$var wire 64 ~ Y_FLAT [63:0] $end
$var wire 32 !" X [31:0] $end
$var wire 64 "" W_FLAT [63:0] $end
$var wire 64 #" B_FLAT [63:0] $end
$var parameter 32 $" ACC_W $end
$var parameter 32 %" DW $end
$var parameter 32 &" N_IN $end
$var parameter 32 '" N_OUT $end
$scope begin NEURON[0] $end
$var parameter 2 (" j $end
$scope module u_neuron $end
$var wire 32 )" B [31:0] $end
$var wire 32 *" W [31:0] $end
$var wire 1 ) clk $end
$var wire 1 * rst $end
$var wire 32 +" X [31:0] $end
$var parameter 32 ," ACC_W $end
$var parameter 32 -" DW $end
$var parameter 32 ." N $end
$var reg 32 /" OUT [31:0] $end
$var reg 32 0" sum_comb [31:0] $end
$var integer 32 1" k [31:0] $end
$scope begin MULT[0] $end
$var parameter 2 2" i $end
$upscope $end
$scope begin MULT[1] $end
$var parameter 2 3" i $end
$upscope $end
$scope begin MULT[2] $end
$var parameter 3 4" i $end
$upscope $end
$scope begin MULT[3] $end
$var parameter 3 5" i $end
$upscope $end
$upscope $end
$upscope $end
$scope begin NEURON[1] $end
$var parameter 2 6" j $end
$scope module u_neuron $end
$var wire 32 7" B [31:0] $end
$var wire 32 8" W [31:0] $end
$var wire 1 ) clk $end
$var wire 1 * rst $end
$var wire 32 9" X [31:0] $end
$var parameter 32 :" ACC_W $end
$var parameter 32 ;" DW $end
$var parameter 32 <" N $end
$var reg 32 =" OUT [31:0] $end
$var reg 32 >" sum_comb [31:0] $end
$var integer 32 ?" k [31:0] $end
$scope begin MULT[0] $end
$var parameter 2 @" i $end
$upscope $end
$scope begin MULT[1] $end
$var parameter 2 A" i $end
$upscope $end
$scope begin MULT[2] $end
$var parameter 3 B" i $end
$upscope $end
$scope begin MULT[3] $end
$var parameter 3 C" i $end
$upscope $end
$upscope $end
$upscope $end
$upscope $end
$scope module u_requant $end
$var wire 128 D" IN_FLAT [127:0] $end
$var wire 32 E" OUT_FLAT [31:0] $end
$var parameter 32 F" ACC_W $end
$var parameter 32 G" DW $end
$var parameter 8 H" MAX_VAL $end
$var parameter 8 I" MIN_VAL $end
$var parameter 32 J" N $end
$scope begin SAT[0] $end
$var wire 32 K" val [31:0] $end
$var parameter 2 L" i $end
$upscope $end
$scope begin SAT[1] $end
$var wire 32 M" val [31:0] $end
$var parameter 2 N" i $end
$upscope $end
$scope begin SAT[2] $end
$var wire 32 O" val [31:0] $end
$var parameter 3 P" i $end
$upscope $end
$scope begin SAT[3] $end
$var wire 32 Q" val [31:0] $end
$var parameter 3 R" i $end
$upscope $end
$upscope $end
$scope module u_w1 $end
$var wire 128 S" W_FLAT [127:0] $end
$var wire 128 T" B_FLAT [127:0] $end
$var parameter 32 U" ACC_W $end
$var parameter 32 V" DW $end
$upscope $end
$scope module u_w2 $end
$var wire 64 W" W_FLAT [63:0] $end
$var wire 64 X" B_FLAT [63:0] $end
$var parameter 32 Y" ACC_W $end
$var parameter 32 Z" DW $end
$upscope $end
$upscope $end
$upscope $end
$enddefinitions $end
$comment Show the parameter values. $end
$dumpall
b1000 Z"
b100000 Y"
b1000 V"
b100000 U"
b11 R"
b10 P"
b1 N"
b0 L"
b100 J"
b10000000 I"
b1111111 H"
b1000 G"
b100000 F"
b11 C"
b10 B"
b1 A"
b0 @"
b100 <"
b1000 ;"
b100000 :"
b1 6"
b11 5"
b10 4"
b1 3"
b0 2"
b100 ."
b1000 -"
b100000 ,"
b0 ("
b10 '"
b100 &"
b1000 %"
b100000 $"
b11 }
b10 |
b1 {
b0 z
b100 v
b1000 u
b100000 t
b11 p
b11 o
b10 n
b1 m
b0 l
b100 h
b1000 g
b100000 f
b10 b
b11 a
b10 `
b1 _
b0 ^
b100 Z
b1000 Y
b100000 X
b1 T
b11 S
b10 R
b1 Q
b0 P
b100 L
b1000 K
b100000 J
b0 F
b100 E
b100 D
b1000 C
b100000 B
b1 <
b11 ;
b10 :
b0 9
b100 8
b1000 6
b100000 5
b1000 '
b100000 &
$end
#0
$dumpvars
b1111111111111111111111111111111000000000000000000000000000000000 X"
b100000001000000000000000000000000000000000000000100000001 W"
b1111111111111111111111111111111010000000000000000000000000000000000000000000000000000000000000000 T"
b10000000000000000000000000000000000000000000000000000000101111111100000001111111110000000100000001000000010000000100000001 S"
b0 Q"
b0 O"
b0 M"
b0 K"
b0 E"
b0 D"
b100 ?"
b11111111111111111111111111111110 >"
b0 ="
b0 9"
b1000000010000000000000000 8"
b11111111111111111111111111111110 7"
b100 1"
b0 0"
b0 /"
b0 +"
b100000001 *"
b0 )"
b1111111111111111111111111111111000000000000000000000000000000000 #"
b100000001000000000000000000000000000000000000000100000001 ""
b0 !"
b0 ~
b100 y
b1 x
b0 w
b0 s
b10000000000000000000000000 r
b1 q
b100 k
b11111111111111111111111111111101 j
b0 i
b0 e
b10 d
b11111111111111111111111111111101 c
b100 ]
b0 \
b0 [
b0 W
b11111111000000011111111100000001 V
b0 U
b100 O
b0 N
b0 M
b0 I
b1000000010000000100000001 H
b0 G
b1111111111111111111111111111111010000000000000000000000000000000000000000000000000000000000000000 A
b10000000000000000000000000000000000000000000000000000000101111111100000001111111110000000100000001000000010000000100000001 @
b0 ?
b0 >
b0 =
b0 7
b0 4
b0 3
b1111111111111111111111111111111010000000000000000000000000000000000000000000000000000000000000000 2
b10000000000000000000000000000000000000000000000000000000101111111100000001111111110000000100000001000000010000000100000001 1
b0 0
b0 /
b1111111111111111111111111111111000000000000000000000000000000000 .
b100000001000000000000000000000000000000000000000100000001 -
b0 ,
0+
1*
0)
b0 (
b0 %
b0 $
0#
b0 "
b0 !
$end
#5000
1)
#10000
0)
#12000
0*
#15000
b100 ?"
b11111111111111111111111111111111 >"
b1000000000000000000000000 /
b1000000000000000000000000 !"
b1000000000000000000000000 +"
b1000000000000000000000000 9"
b1000000000000000000000000 E"
b1 Q"
b1000000000000000000000000000000000000000000000000000000000000000000000000000000000000000000000000 0
b1000000000000000000000000000000000000000000000000000000000000000000000000000000000000000000000000 ?
b1000000000000000000000000000000000000000000000000000000000000000000000000000000000000000000000000 D"
b1 w
1)
#20000
0)
#22000
b1000 N
b100 O
b11111111111111111111111111111010 \
b100 ]
b100 k
b1 j
b100 y
b1001 x
1+
b100111111110000001100000010 (
b100111111110000001100000010 ,
b100111111110000001100000010 >
b100111111110000001100000010 I
b100111111110000001100000010 W
b100111111110000001100000010 e
b100111111110000001100000010 s
#25000
b100 ?"
b1000 >"
b1000 0"
b100 1"
b1001000000010000000000001000 /
b1001000000010000000000001000 !"
b1001000000010000000000001000 +"
b1001000000010000000000001000 9"
b1001000000010000000000001000 E"
b1001 Q"
b1 O"
b1000 K"
b1 $
b1 3
b1 7
b1 =
b1001 w
b1 i
b1001000000000000000000000000000000010000000000000000000000000000000000000000000000000000000000001000 0
b1001000000000000000000000000000000010000000000000000000000000000000000000000000000000000000000001000 ?
b1001000000000000000000000000000000010000000000000000000000000000000000000000000000000000000000001000 D"
b1000 M
1)
#30000
0)
#32000
0+
#35000
b1000 "
b1000 !
b1000 /"
b100000000000000000000000000000001000 %
b100000000000000000000000000000001000 4
b100000000000000000000000000000001000 ~
b1000 ="
b10 $
b10 3
b10 7
b10 =
1)
#40000
0)
#45000
b11 $
b11 3
b11 7
b11 =
1)
#50000
0)
#55000
b100 $
b100 3
b100 7
b100 =
1)
#60000
0)
#65000
b0 $
b0 3
b0 7
b0 =
1#
1)
#70000
0)
#72000
b100 O
b0 N
b100 ]
b0 \
b100 k
b11111111111111111111111111111101 j
b100 y
b1 x
1+
b0 (
b0 ,
b0 >
b0 I
b0 W
b0 e
b0 s
#75000
b100 1"
b0 0"
b100 ?"
b11111111111111111111111111111111 >"
b1000000000000000000000000 /
b1000000000000000000000000 !"
b1000000000000000000000000 +"
b1000000000000000000000000 9"
b1000000000000000000000000 E"
b0 K"
b0 O"
b1 Q"
b0 M
b0 i
b1000000000000000000000000000000000000000000000000000000000000000000000000000000000000000000000000 0
b1000000000000000000000000000000000000000000000000000000000000000000000000000000000000000000000000 ?
b1000000000000000000000000000000000000000000000000000000000000000000000000000000000000000000000000 D"
b1 w
b1 $
b1 3
b1 7
b1 =
0#
1)
#80000
0)
#82000
0+
#85000
b0 !
b0 "
b10 $
b10 3
b10 7
b10 =
b0 ="
b0 %
b0 4
b0 ~
b0 /"
1)
#90000
0)
#95000
b11 $
b11 3
b11 7
b11 =
1)
#100000
0)
#105000
b100 $
b100 3
b100 7
b100 =
1)
#110000
0)
#115000
b0 $
b0 3
b0 7
b0 =
1#
1)
#120000
0)
#122000
b10100 N
b100 O
b0 \
b100 ]
b100 k
b111 j
b100 y
b1011 x
1+
b101000001010000010100000101 (
b101000001010000010100000101 ,
b101000001010000010100000101 >
b101000001010000010100000101 I
b101000001010000010100000101 W
b101000001010000010100000101 e
b101000001010000010100000101 s
#125000
b100 ?"
b10000 >"
b10100 0"
b100 1"
b1011000001110000000000010100 /
b1011000001110000000000010100 !"
b1011000001110000000000010100 +"
b1011000001110000000000010100 9"
b1011000001110000000000010100 E"
b1011 Q"
b111 O"
b10100 K"
b1 $
b1 3
b1 7
b1 =
0#
b1011 w
b111 i
b1011000000000000000000000000000001110000000000000000000000000000000000000000000000000000000000010100 0
b1011000000000000000000000000000001110000000000000000000000000000000000000000000000000000000000010100 ?
b1011000000000000000000000000000001110000000000000000000000000000000000000000000000000000000000010100 D"
b10100 M
1)
#130000
0)
#132000
0+
#135000
b10100 "
b10000 !
b10100 /"
b1000000000000000000000000000000010100 %
b1000000000000000000000000000000010100 4
b1000000000000000000000000000000010100 ~
b10000 ="
b10 $
b10 3
b10 7
b10 =
1)
#140000
0)
#145000
b11 $
b11 3
b11 7
b11 =
1)
#150000
0)
#155000
b100 $
b100 3
b100 7
b100 =
1)
#160000
0)
#165000
b0 $
b0 3
b0 7
b0 =
1#
1)
