AI_Accel/Mac/mac_dot.v
module mac_dot(
input clk,
input rst,
input signed [15:0]I,
input signed [15:0]W,
input signed [31:0]B,
output reg [31:0]OUT
);

wire [7:0] p0,p1,p2,p3;

assign p0 = I[15:12] * W[15:12];
assign p1 = I[11:8]  * W[11:8];
assign p2 = I[7:4]   * W[7:4];
assign p3 = I[3:0]   * W[3:0];

reg signed [15:0]SUM;

always @(posedge clk or posedge rst)
begin
    if(rst) begin
        SUM <= 0;
        OUT <= 0;
    end
    else begin
        SUM <= p0 + p1 + p2 + p3 + B;

        if(SUM < 0)
            OUT <= 0;
        else
            OUT <= SUM;
    end
end

endmodule

AI_Accel/Mac/tb_mac_dot.v
`timescale 1ns/1ps

module tb_mac_dot;

    reg clk;
    reg rst;
    reg signed [15:0] I;
    reg signed [15:0] W;
    reg signed [31:0] B;
    wire signed [31:0]SUM;
    wire [31:0] OUT;

    mac_dot uut(
        .clk(clk),
        .rst(rst),
        .I(I),
        .W(W),
        .B(B),
        .OUT(OUT)
    );

    initial begin
        clk = 0;
        forever #5 clk = ~clk;
    end

    initial begin

        $dumpfile("mac_dot.vcd");
        $dumpvars(0, tb_mac_dot);

        $monitor("Time=%0t rst=%b I=%h W=%h bais=%h OUT=%d",
                  $time, rst, I, W, B, OUT);

        rst = 0;
        I   = 0;
        W   = 0;
        B = 0;
        #12;

        rst = 0;
        I = {16'd0,4'd2,4'd4,4'd6,4'd8};
        W = {16'd0,4'd3,4'd5,4'd7,4'd9};
        B = -200;
        #20;

        rst = 1;
        I = {16'd0,4'd3,4'd4,4'd5,4'd6};
        W = {16'd0,4'd3,4'd4,4'd5,4'd6};
        B = 32'd43;
        #20;

        rst = 0;
        I = {16'd0,4'd1,4'd2,4'd3,4'd4};
        W = {16'd0,4'd8,4'd7,4'd6,4'd5};
        B = 32'd43;
        #20;

        $finish;

    end
endmodule

AI_Accel/Mac/mac_dot.vcd
$date
	Fri Jun 12 10:10:56 2026
$end
$version
	Icarus Verilog
$end
$timescale
	1ps
$end
$scope module tb_mac_dot $end
$var wire 32 ! OUT [31:0] $end
$var reg 32 " B [31:0] $end
$var reg 16 # I [15:0] $end
$var reg 16 $ W [15:0] $end
$var reg 1 % clk $end
$var reg 1 & rst $end
$scope module uut $end
$var wire 32 ' B [31:0] $end
$var wire 16 ( I [15:0] $end
$var wire 16 ) W [15:0] $end
$var wire 1 % clk $end
$var wire 1 & rst $end
$var wire 8 * p3 [7:0] $end
$var wire 8 + p2 [7:0] $end
$var wire 8 , p1 [7:0] $end
$var wire 8 - p0 [7:0] $end
$var reg 32 . OUT [31:0] $end
$var reg 16 / SUM [15:0] $end
$upscope $end
$upscope $end
$enddefinitions $end
$comment Show the parameter values. $end
$dumpall
$end
#0
$dumpvars
bx /
bx .
b0 -
b0 ,
b0 +
b0 *
b0 )
b0 (
b0 '
0&
0%
b0 $
b0 #
b0 "
bx !
$end
#5000
b0 /
1%
#10000
0%
#12000
b110 -
b10100 ,
b101010 +
b1001000 *
b11111111111111111111111100111000 "
b11111111111111111111111100111000 '
b11010101111001 $
b11010101111001 )
b10010001101000 #
b10010001101000 (
#15000
b0 !
b0 .
b1111111111000100 /
1%
#20000
0%
#25000
1%
#30000
0%
#32000
b0 /
b10000 ,
b1001 -
b11001 +
b100100 *
b101011 "
b101011 '
b11010001010110 $
b11010001010110 )
b11010001010110 #
b11010001010110 (
1&
#35000
1%
#40000
0%
#45000
1%
#50000
0%
#52000
b1000 -
b1110 ,
b10010 +
b10100 *
b1000011101100101 $
b1000011101100101 )
b1001000110100 #
b1001000110100 (
0&
#55000
b1100111 /
1%
#60000
0%
#65000
b1100111 !
b1100111 .
1%
